OSMsimp/__init__.py
OSMsimp/extract_OSM.py
OSMsimp/main.py
OSMsimp/makegraphconnected.py
OSMsimp/merging_networks.py
OSMsimp/merging_networks_V2.py
OSMsimp/simplification_A.py
OSMsimp/simplification_B.py
netsimp/__init__.py
netsimp/extract_OSM.py
netsimp/main.py
netsimp/merging_networks.py
netsimp/simplification_A.py
netsimp/simplification_B.py
OSMsimp-1.0.69.dist-info/LICENCE
OSMsimp-1.0.69.dist-info/METADATA
OSMsimp-1.0.69.dist-info/WHEEL
OSMsimp-1.0.69.dist-info/top_level.txt
OSMsimp-1.0.69.dist-info/RECORD
