Metadata-Version: 2.1
Name: OSMsimp
Version: 1.0.69
Summary: package to simplify networks from OpenstreetMap
Author: Adrien Fauste-Gay
Author-email: adrien.fauste-gay@univ-grenoble-alpes.fr
Classifier: Development Status :: 3 - Alpha
Classifier: Intended Audience :: Science/Research
Classifier: License :: OSI Approved :: GNU General Public License v3 (GPLv3)
Classifier: Programming Language :: Python :: 3.9
License-File: LICENCE
Requires-Dist: setuptools~=65.6.3
Requires-Dist: geopandas~=0.12.2
Requires-Dist: numpy<2,>=1.26.0
Requires-Dist: tqdm~=4.64.1
Requires-Dist: shapely~=2.0.1
Requires-Dist: pyogrio~=0.6.0
Requires-Dist: scikit-learn~=1.2.1
Requires-Dist: osmnx~=1.3.0
Requires-Dist: networkx~=2.8.4
Requires-Dist: pandas~=1.5.3
Requires-Dist: progressbar~=2.5
Requires-Dist: esy~=1.2.0
Requires-Dist: esy-osm-pbf~=0.0.1
Requires-Dist: esy-osmfilter~=1.0.11
Requires-Dist: protobuf==3.20.3
Requires-Dist: fiona~=1.9.5
Requires-Dist: geopy~=2.4.1
